[
  {
    "weight": 0.813,
    "price": 2.536,
    "class": "pears"
  },
  {
    "weight": 1.53,
    "price": 3.108,
    "class": "pears"
  },
  {
    "weight": 0.789,
    "price": 2.374,
    "class": "pears"
  },
  {
    "weight": 0.708,
    "price": 2.602,
    "class": "pears"
  },
  {
    "weight": 0.776,
    "price": 2.829,
    "class": "pears"
  },
  {
    "weight": 0.655,
    "price": 3.24,
    "class": "pears"
  },
  {
    "weight": 1.172,
    "price": 3.026,
    "class": "pears"
  },
  {
    "weight": 0.873,
    "price": 3.076,
    "class": "pears"
  },
  {
    "weight": 0.261,
    "price": 2.864,
    "class": "pears"
  },
  {
    "weight": 1.371,
    "price": 2.614,
    "class": "pears"
  },
  {
    "weight": 1.026,
    "price": 3.346,
    "class": "pears"
  },
  {
    "weight": 1.097,
    "price": 3.386,
    "class": "pears"
  },
  {
    "weight": 0.876,
    "price": 2.857,
    "class": "pears"
  },
  {
    "weight": 0.629,
    "price": 2.574,
    "class": "pears"
  },
  {
    "weight": 1.205,
    "price": 3.069,
    "class": "pears"
  },
  {
    "weight": 0.154,
    "price": 3.338,
    "class": "pears"
  },
  {
    "weight": 1.164,
    "price": 2.48,
    "class": "pears"
  },
  {
    "weight": 1.078,
    "price": 2.552,
    "class": "pears"
  },
  {
    "weight": 0.804,
    "price": 3.088,
    "class": "pears"
  },
  {
    "weight": 1.16,
    "price": 3.105,
    "class": "pears"
  },
  {
    "weight": 1.316,
    "price": 3.399,
    "class": "pears"
  },
  {
    "weight": 1.489,
    "price": 2.835,
    "class": "pears"
  },
  {
    "weight": 1.392,
    "price": 2.684,
    "class": "pears"
  },
  {
    "weight": 0.689,
    "price": 2.785,
    "class": "pears"
  },
  {
    "weight": 0.908,
    "price": 3.688,
    "class": "pears"
  },
  {
    "weight": 0.895,
    "price": 2.441,
    "class": "pears"
  },
  {
    "weight": 1.583,
    "price": 3.339,
    "class": "pears"
  },
  {
    "weight": 0.833,
    "price": 2.663,
    "class": "pears"
  },
  {
    "weight": 1.703,
    "price": 2.999,
    "class": "pears"
  },
  {
    "weight": 1.203,
    "price": 2.558,
    "class": "pears"
  },
  {
    "weight": 1.486,
    "price": 3.167,
    "class": "pears"
  },
  {
    "weight": 0.861,
    "price": 4.056,
    "class": "pears"
  },
  {
    "weight": 1.214,
    "price": 3.228,
    "class": "pears"
  },
  {
    "weight": 1.523,
    "price": 2.612,
    "class": "pears"
  },
  {
    "weight": 1.433,
    "price": 3.203,
    "class": "pears"
  },
  {
    "weight": 1.394,
    "price": 2.368,
    "class": "pears"
  },
  {
    "weight": 1.375,
    "price": 2.835,
    "class": "pears"
  },
  {
    "weight": 1.003,
    "price": 2.916,
    "class": "pears"
  },
  {
    "weight": 0.964,
    "price": 3.321,
    "class": "pears"
  },
  {
    "weight": 1.15,
    "price": 2.987,
    "class": "pears"
  },
  {
    "weight": 3.349,
    "price": 1.454,
    "class": "blueberries"
  },
  {
    "weight": 4.427,
    "price": 1.239,
    "class": "blueberries"
  },
  {
    "weight": 4.735,
    "price": 1.11,
    "class": "blueberries"
  },
  {
    "weight": 3.435,
    "price": 0.731,
    "class": "blueberries"
  },
  {
    "weight": 3.668,
    "price": 0.601,
    "class": "blueberries"
  },
  {
    "weight": 3.87,
    "price": 1.462,
    "class": "blueberries"
  },
  {
    "weight": 4.025,
    "price": 0.792,
    "class": "blueberries"
  },
  {
    "weight": 4.122,
    "price": 0.986,
    "class": "blueberries"
  },
  {
    "weight": 4.423,
    "price": 0.85,
    "class": "blueberries"
  },
  {
    "weight": 4.021,
    "price": 1.445,
    "class": "blueberries"
  },
  {
    "weight": 4.632,
    "price": 0.177,
    "class": "blueberries"
  },
  {
    "weight": 4.33,
    "price": 1.138,
    "class": "blueberries"
  },
  {
    "weight": 3.96,
    "price": 1.022,
    "class": "blueberries"
  },
  {
    "weight": 3.711,
    "price": 1.07,
    "class": "blueberries"
  },
  {
    "weight": 4.203,
    "price": 0.611,
    "class": "blueberries"
  },
  {
    "weight": 4.2,
    "price": 0.477,
    "class": "blueberries"
  },
  {
    "weight": 3.069,
    "price": 1.063,
    "class": "blueberries"
  },
  {
    "weight": 3.973,
    "price": 0.825,
    "class": "blueberries"
  },
  {
    "weight": 4.098,
    "price": 1.127,
    "class": "blueberries"
  },
  {
    "weight": 4.047,
    "price": 1.058,
    "class": "blueberries"
  },
  {
    "weight": 3.332,
    "price": 1.175,
    "class": "blueberries"
  },
  {
    "weight": 3.986,
    "price": 0.381,
    "class": "blueberries"
  },
  {
    "weight": 3.81,
    "price": 1.902,
    "class": "blueberries"
  },
  {
    "weight": 3.756,
    "price": 0.824,
    "class": "blueberries"
  },
  {
    "weight": 4.267,
    "price": 0.879,
    "class": "blueberries"
  },
  {
    "weight": 4.41,
    "price": 0.644,
    "class": "blueberries"
  },
  {
    "weight": 3.625,
    "price": 0.462,
    "class": "blueberries"
  },
  {
    "weight": 4.05,
    "price": 1.195,
    "class": "blueberries"
  },
  {
    "weight": 4.405,
    "price": 0.743,
    "class": "blueberries"
  },
  {
    "weight": 2.508,
    "price": 1.289,
    "class": "blueberries"
  },
  {
    "weight": 3.966,
    "price": 1.141,
    "class": "blueberries"
  },
  {
    "weight": 3.636,
    "price": 0.32,
    "class": "blueberries"
  },
  {
    "weight": 4.027,
    "price": 0.394,
    "class": "blueberries"
  },
  {
    "weight": 3.837,
    "price": 1.385,
    "class": "blueberries"
  },
  {
    "weight": 3.86,
    "price": 1.08,
    "class": "blueberries"
  },
  {
    "weight": 3.871,
    "price": 1.043,
    "class": "blueberries"
  },
  {
    "weight": 3.594,
    "price": 1.117,
    "class": "blueberries"
  },
  {
    "weight": 3.483,
    "price": 1.56,
    "class": "blueberries"
  },
  {
    "weight": 3.597,
    "price": 0.584,
    "class": "blueberries"
  },
  {
    "weight": 4.317,
    "price": 0.826,
    "class": "blueberries"
  },
  {
    "weight": 1,
    "price": 3,
    "class": "unknown"
  }
]
